ganutils/__init__.py
ganutils/algorithms/__init__.py
ganutils/api/__init__.py
ganutils/api/github/__init__.py
ganutils/api/github/client.py
ganutils/api/github/endpoints.py
ganutils/api/twilio/__init__.py
ganutils/api/twilio/client.py
ganutils/data/__init__.py
ganutils/data/featurizer.py
ganutils/data/tfidf.py
ganutils/data/text/__init__.py
ganutils/data/text/preprocess.py
ganutils/scripts/__init__.py
ganutils/utils/__init__.py
ganutils/utils/concurrency.py
ganutils/utils/file.py
ganutils/utils/iterable.py
ganutils/utils/url.py
ganutils-2.2.dist-info/LICENSE.txt
ganutils-2.2.dist-info/METADATA
ganutils-2.2.dist-info/WHEEL
ganutils-2.2.dist-info/top_level.txt
ganutils-2.2.dist-info/RECORD
